nepali_toolkit/__init__.py
nepali_toolkit/helpers.py
nepali_toolkit/random_utils.py
nepali_toolkit/utils.py
nepali_toolkit/validators.py
nepali_toolkit/data/__init__.py
nepali_toolkit/data/digits_map.json
nepali_toolkit/data/districts.json
nepali_toolkit/data/municipalities.json
nepali_toolkit/data/number_words_map.json
nepali_toolkit/data/postal_codes.json
nepali_toolkit/data/provinces.json
nepali_toolkit/locations/__init__.py
nepali_toolkit/locations/location_data.py
nepali_toolkit/numbers/__init__.py
nepali_toolkit/numbers/convert.py
nepali_toolkit/numbers/words.py
nepali_toolkit-0.1.3.dist-info/licenses/LICENSE
nepali_toolkit-0.1.3.dist-info/METADATA
nepali_toolkit-0.1.3.dist-info/WHEEL
nepali_toolkit-0.1.3.dist-info/top_level.txt
nepali_toolkit-0.1.3.dist-info/RECORD
