Metadata-Version: 2.4
Name: nepali-toolkit
Version: 0.1.3
Summary: A collection of tools for working with Nepali data, digits, dates and more.
Author-email: Bibek Joshi <bibekjoshi34@gmail.com>
License-Expression: MIT
Project-URL: Homepage, https://github.com/bibekjoshi01/nepali-toolkit
Keywords: nepali,districts,municipalities,validators,postal codes,bs,b.s,date,datetime,time,timezone,nepal,bikram,nepali-date,nepali-datetime,nepal-time,npt,nepal-timezone
Classifier: Programming Language :: Python :: 3
Classifier: Operating System :: OS Independent
Requires-Python: >=3.10
License-File: LICENSE
Dynamic: license-file
